goodreads_book_quotes/__init__.py
goodreads_quotes/__init__.py
goodreads_book_quotes-0.0.3.dist-info/LICENSE
goodreads_book_quotes-0.0.3.dist-info/METADATA
goodreads_book_quotes-0.0.3.dist-info/WHEEL
goodreads_book_quotes-0.0.3.dist-info/top_level.txt
goodreads_book_quotes-0.0.3.dist-info/RECORD
